django_typed_settings/__init__.py
django_typed_settings/booleans.py
django_typed_settings/database.py
django_typed_settings/environ.py
django_typed_settings/exceptions.py
django_typed_settings/logging_level.py
django_typed_settings/timedelta.py
django_typed_settings-0.1.1.dist-info/LICENSE
django_typed_settings-0.1.1.dist-info/METADATA
django_typed_settings-0.1.1.dist-info/WHEEL
django_typed_settings-0.1.1.dist-info/RECORD
