Metadata-Version: 2.3
Name: django-typed-settings
Version: 0.1.1
Summary: Type validation for bare django configuration settings system
License: MIT
Author: Kirill Zhosul
Author-email: <kirillzhosul@yandex.com
Requires-Python: >=3.12
Classifier: License :: OSI Approved :: MIT License
Classifier: Programming Language :: Python :: 3
Classifier: Programming Language :: Python :: 3.12
Classifier: Programming Language :: Python :: 3.13
